README.md
setup.py
body_crop/__init__.py
body_crop/__main__.py
body_crop/body.py
body_crop.egg-info/PKG-INFO
body_crop.egg-info/SOURCES.txt
body_crop.egg-info/dependency_links.txt
body_crop.egg-info/top_level.txt