Metadata-Version: 1.1
Name: body-crop
Version: 0.9
Summary: Tool for cropping files
Home-page: https://github.com/mblahay/body
Author: Michael Blahay
Author-email: mblahay@gmail.com
License: MIT
Keywords: body_crop
Platform: UNKNOWN
Classifier: Development Status :: 3 - Alpha
Classifier: Topic :: Utilities
